setup.cfg
setup.py
Vol4onok/__init__.py
Vol4onok/Терминал.py
Vol4onok/взаимодействие_с_ТГ.py
Vol4onok/проверка_элементов.py
Vol4onok/работа_с_файлами.py
Vol4onok/файловая_система.py
Vol4onok.egg-info/PKG-INFO
Vol4onok.egg-info/SOURCES.txt
Vol4onok.egg-info/dependency_links.txt
Vol4onok.egg-info/not-zip-safe
Vol4onok.egg-info/top_level.txt