Metadata-Version: 2.1
Name: Vol4onok
Version: 1.0
Summary: Мои личные инструменты
Author-email: akkiravolkov@gmail.com
